BasicAugmentation/__init__.py
BasicAugmentation/basic_augmentation.py
ImageAugment/__init__.py
ImageAugment/basic_augmentation.py
image_augment-0.1.dist-info/LICENSE
image_augment-0.1.dist-info/METADATA
image_augment-0.1.dist-info/WHEEL
image_augment-0.1.dist-info/top_level.txt
image_augment-0.1.dist-info/RECORD
