Metadata-Version: 2.1
Name: image-augment
Version: 0.1
Summary: Basic image augmentor
Home-page: https://github.com/lewis-morris/image_augment
Author: lewis
Author-email: lewis.morris@gmail.com
License: MIT
Download-URL: https://github.com/lewis-morris/image_augment/archive/0.1.tar.gz
Platform: UNKNOWN
